head_breaker/__init__.py
head_breaker/breaker.py
head_breaker/main.py
head_breaker/version.py
h_breaker-1.0.0.dist-info/LICENSE.txt
h_breaker-1.0.0.dist-info/METADATA
h_breaker-1.0.0.dist-info/WHEEL
h_breaker-1.0.0.dist-info/entry_points.txt
h_breaker-1.0.0.dist-info/top_level.txt
h_breaker-1.0.0.dist-info/zip-safe
h_breaker-1.0.0.dist-info/RECORD
